odoo/addons/l10n_es_aeat_certificate/README.rst
odoo/addons/l10n_es_aeat_certificate/__init__.py
odoo/addons/l10n_es_aeat_certificate/__manifest__.py
odoo/addons/l10n_es_aeat_certificate/i18n/ca.po
odoo/addons/l10n_es_aeat_certificate/i18n/es.po
odoo/addons/l10n_es_aeat_certificate/i18n/l10n_es_aeat_certificate.pot
odoo/addons/l10n_es_aeat_certificate/models/__init__.py
odoo/addons/l10n_es_aeat_certificate/models/aeat_certificate.py
odoo/addons/l10n_es_aeat_certificate/security/aeat_certificate_security.xml
odoo/addons/l10n_es_aeat_certificate/security/ir.model.access.csv
odoo/addons/l10n_es_aeat_certificate/static/description/icon.png
odoo/addons/l10n_es_aeat_certificate/views/aeat_certificate_view.xml
odoo/addons/l10n_es_aeat_certificate/wizards/__init__.py
odoo/addons/l10n_es_aeat_certificate/wizards/aeat_certificate_password.py
odoo/addons/l10n_es_aeat_certificate/wizards/aeat_certificate_password_view.xml
odoo11_addon_l10n_es_aeat_certificate-11.0.1.0.1.dist-info/METADATA
odoo11_addon_l10n_es_aeat_certificate-11.0.1.0.1.dist-info/WHEEL
odoo11_addon_l10n_es_aeat_certificate-11.0.1.0.1.dist-info/top_level.txt
odoo11_addon_l10n_es_aeat_certificate-11.0.1.0.1.dist-info/RECORD
